furosh/__init__.py
furosh/__main__.py
furosh/cli.py
furosh-0.1.1.dist-info/METADATA
furosh-0.1.1.dist-info/WHEEL
furosh-0.1.1.dist-info/RECORD
