Metadata-Version: 2.1
Name: furosh
Version: 0.1.1
Summary: 
Author: Vijay Selvaraj
Author-email: vijay.selvaraj@gmail.com
Requires-Python: >=3.12,<4.0
Classifier: Programming Language :: Python :: 3
Classifier: Programming Language :: Python :: 3.12
Requires-Dist: click (>=8.1.7,<9.0.0)
